pygoodpractices/___init__.py
pygoodpractices/config_generator.py
pygoodpractices/initializer.py
pygoodpractices/installer.py
pygoodpractices/precommit_runner.py
pygoodpractices-0.1.0.dist-info/LICENSE
pygoodpractices-0.1.0.dist-info/METADATA
pygoodpractices-0.1.0.dist-info/WHEEL
pygoodpractices-0.1.0.dist-info/entry_points.txt
pygoodpractices-0.1.0.dist-info/top_level.txt
pygoodpractices-0.1.0.dist-info/RECORD
