Metadata-Version: 2.2
Name: pygoodpractices
Version: 0.1.0
Summary: A tool to set up pre-commit hooks automatically
Author: petudeveloper
License: Apache-2.0
Keywords: pre-commit,automation,best practices
Classifier: Development Status :: 4 - Beta
Classifier: License :: OSI Approved :: Apache Software License
Classifier: Programming Language :: Python :: 3
Classifier: Programming Language :: Python :: 3.7
Classifier: Programming Language :: Python :: 3.8
Classifier: Programming Language :: Python :: 3.9
Classifier: Programming Language :: Python :: 3.10
Classifier: Programming Language :: Python :: 3.11
Requires-Python: >=3.7
License-File: LICENSE
Requires-Dist: pre-commit
Requires-Dist: virtualenv>=20.0.0
